{
  "id": "discord-scrape-members",
  "name": "discord_scrape_members",
  "description": "Scrape the member list of a Discord server. Returns usernames and roles for visible members.",
  "version": "1.0.0",
  "parameters": [
    {
      "name": "channel_url",
      "type": "string",
      "description": "Any channel URL in the server (e.g. 'https://discord.com/channels/123/456')",
      "required": true
    }
  ],
  "steps": [
    {
      "action": "navigate",
      "url": "{{channel_url}}",
      "label": "Open Discord channel"
    },
    {
      "action": "waitForSelector",
      "selector": "div[role='textbox']",
      "timeout": 15000,
      "label": "Wait for channel to load"
    },
    {
      "action": "wait",
      "ms": 2000
    },
    {
      "action": "code",
      "code": "const membersToggle = document.querySelector('button[aria-label*=\"Member\"], button[aria-label*=\"member\"]'); if (membersToggle) membersToggle.click(); return { toggled: true }",
      "name": "show_members",
      "label": "Show member list"
    },
    {
      "action": "wait",
      "ms": 2000
    },
    {
      "action": "code",
      "code": "const members = []; const memberList = document.querySelector('[aria-label=\"Members\"]') || document.querySelector('aside div[data-list-id=\"members\"]'); if (!memberList) { return { member_count: 0, members: [], error: 'Member list not found. It may be hidden or you may need to toggle it.' }; } let currentRole = ''; const items = memberList.querySelectorAll('[data-list-item-id]'); for (const el of items) { const itemId = el.getAttribute('data-list-item-id') || ''; if (itemId.startsWith('members-')) { const roleText = el.querySelector('h2, h3, span'); if (roleText) { currentRole = roleText.textContent.trim().replace(/\\s*—\\s*\\d+$/, '').replace(/\\s*\\d+$/, ''); continue; } } const nameEl = el.querySelector('[class*=\"username\"] span, [class*=\"name\"] span, span[class*=\"roleColor\"]'); if (!nameEl) { const innerSpans = el.querySelectorAll('span'); for (const s of innerSpans) { if (s.textContent.trim() && s.textContent.trim().length < 50 && !s.querySelector('span')) { members.push({ username: s.textContent.trim(), role: currentRole, status: '' }); break; } } continue; } const statusEl = el.querySelector('[aria-label*=\"status\"], [class*=\"status\"]'); members.push({ username: nameEl.textContent.trim(), role: currentRole, status: statusEl ? statusEl.getAttribute('aria-label') || statusEl.textContent.trim() : '' }); } return { member_count: members.length, members: members.slice(0, 50) }",
      "name": "members_list",
      "label": "Extract member list"
    }
  ]
}
